{
    "Ar36": {
        "error": 0.00012112245114182915,
        "error_type": "SEM",
        "filter_outliers_dict": {
            "filter_outliers": true,
            "iterations": 1,
            "std_devs": 2
        },
        "fit": "Linear",
        "value": 0.009355584963085271
    },
    "Ar37": {
        "error": 0.0045514231082467325,
        "error_type": "SEM",
        "filter_outliers_dict": {
            "filter_outliers": true,
            "iterations": 1,
            "std_devs": 2
        },
        "fit": "Linear",
        "value": 0.03506571121898561
    },
    "Ar38": {
        "error": 0.009094655008198622,
        "error_type": "SEM",
        "filter_outliers_dict": {
            "filter_outliers": true,
            "iterations": 1,
            "std_devs": 2
        },
        "fit": "Linear",
        "value": -0.0808373728501737
    },
    "Ar39": {
        "error": 0.006783003388564213,
        "error_type": "SEM",
        "filter_outliers_dict": {
            "filter_outliers": true,
            "iterations": 1,
            "std_devs": 2
        },
        "fit": "Parabolic",
        "value": 0.01591373238747146
    },
    "Ar40": {
        "error": 0.01557803228619425,
        "error_type": "SEM",
        "filter_outliers_dict": {
            "filter_outliers": true,
            "iterations": 1,
            "std_devs": 2
        },
        "fit": "Parabolic",
        "value": 2.4077908940924764
    },
    "Ar41": {
        "error": 0.008815850662224272,
        "error_type": "SEM",
        "filter_outliers_dict": {
            "filter_outliers": true,
            "iterations": 1,
            "std_devs": 2
        },
        "fit": "Linear",
        "value": -0.11499534470922194
    }
}